ardutest/__init__.py
ardutest/__main__.py
ardutest/blackbox.py
ardutest/config.py
ardutest/module.py
ardutest/storage.py
ardutest-0.1.2.dist-info/entry_points.txt
ardutest-0.1.2.dist-info/WHEEL
ardutest-0.1.2.dist-info/METADATA
ardutest-0.1.2.dist-info/RECORD
